setup.py
behave_web_api_extended/__init__.py
behave_web_api_extended.egg-info/PKG-INFO
behave_web_api_extended.egg-info/SOURCES.txt
behave_web_api_extended.egg-info/dependency_links.txt
behave_web_api_extended.egg-info/requires.txt
behave_web_api_extended.egg-info/top_level.txt
behave_web_api_extended/steps/__init__.py
behave_web_api_extended/steps/utils.py