Metadata-Version: 1.1
Name: behave-web-api-extended
Version: 0.1.3
Summary: Provides additional testing for JSON APIs with Behave
Home-page: UNKNOWN
Author: Victor Anjos
Author-email: va@deeplearni.ng
License: MIT
Platform: UNKNOWN
Classifier: Operating System :: OS Independent
Classifier: Development Status :: 3 - Alpha
Classifier: Environment :: Web Environment
Classifier: Topic :: Software Development :: Libraries :: Python Modules
Classifier: Topic :: Software Development :: Testing
Classifier: License :: OSI Approved :: MIT License
Classifier: Programming Language :: Python :: 2.7
